meshroom/__init__.py
meshroom/ast.py
meshroom/cli/cli.py
meshroom/decorators.py
meshroom/generic/http_producer.py
meshroom/git.py
meshroom/interaction.py
meshroom/model.py
meshroom/secrets.py
meshroom/template.py
meshroom/templates/init_project/.gitignore
meshroom/templates/init_project/README.md
meshroom/templates/product/README.md
meshroom/templates/product/adversarial_exposure_validation/definition.yaml
meshroom/templates/product/asca/definition.yaml
meshroom/templates/product/assistant/definition.yaml
meshroom/templates/product/caasm/definition.yaml
meshroom/templates/product/cps/definition.yaml
meshroom/templates/product/csma/definition.yaml
meshroom/templates/product/dfir/definition.yaml
meshroom/templates/product/drp/definition.yaml
meshroom/templates/product/easm/definition.yaml
meshroom/templates/product/edr/__init__.py
meshroom/templates/product/edr/definition.yaml
meshroom/templates/product/edr/setup.py
meshroom/templates/product/exposure_assessment/definition.yaml
meshroom/templates/product/itdr/definition.yaml
meshroom/templates/product/mdr/definition.yaml
meshroom/templates/product/monitoring/definition.yaml
meshroom/templates/product/ndr/definition.yaml
meshroom/templates/product/pentest/definition.yaml
meshroom/templates/product/security_service_edge/definition.yaml
meshroom/templates/product/siem/definition.yaml
meshroom/templates/product/telemetry/definition.yaml
meshroom/templates/product/threat_exposure_management/definition.yaml
meshroom/templates/product/tip/definition.yaml
meshroom/templates/product/waf/definition.yaml
meshroom/templates/product/xdr/definition.yaml
meshroom/utils.py
meshroom-0.3.4.dist-info/AUTHORS.md
meshroom-0.3.4.dist-info/LICENSE
meshroom-0.3.4.dist-info/METADATA
meshroom-0.3.4.dist-info/WHEEL
meshroom-0.3.4.dist-info/entry_points.txt
meshroom-0.3.4.dist-info/RECORD
